nolam/__init__.py
nolam/Util/__init__.py
nolam/Util/metrics.py
nolam/algorithm/Action.py
nolam/algorithm/ActionModel.py
nolam/algorithm/Configuration.py
nolam/algorithm/Learner.py
nolam/algorithm/Observation.py
nolam/algorithm/Operator.py
nolam/algorithm/Trace.py
nolam/algorithm/__init__.py
nolam-1.0.0.dist-info/licenses/LICENSE.md
nolam-1.0.0.dist-info/METADATA
nolam-1.0.0.dist-info/WHEEL
nolam-1.0.0.dist-info/top_level.txt
nolam-1.0.0.dist-info/RECORD
